README.md
setup.py
exonum_launcher/__init__.py
exonum_launcher/__main__.py
exonum_launcher/action_result.py
exonum_launcher/cli.py
exonum_launcher/configuration.py
exonum_launcher/explorer.py
exonum_launcher/launch_state.py
exonum_launcher/launcher.py
exonum_launcher/main.py
exonum_launcher/supervisor.py
exonum_launcher.egg-info/PKG-INFO
exonum_launcher.egg-info/SOURCES.txt
exonum_launcher.egg-info/dependency_links.txt
exonum_launcher.egg-info/requires.txt
exonum_launcher.egg-info/top_level.txt
exonum_launcher/instances/__init__.py
exonum_launcher/instances/default_spec_loader.py
exonum_launcher/instances/instance_spec_loader.py
exonum_launcher/runtimes/__init__.py
exonum_launcher/runtimes/runtime.py
exonum_launcher/runtimes/rust.py