Metadata-Version: 2.1
Name: exonum-launcher
Version: 0.2.0
Summary: Exonum Dynamic Services Launcher
Home-page: https://github.com/exonum/exonum-launcher
Author: The Exonum Team
Author-email: contact@exonum.com
License: UNKNOWN
Platform: UNKNOWN
Classifier: Programming Language :: Python :: 3
Classifier: License :: OSI Approved :: Apache Software License
Classifier: Operating System :: OS Independent
Classifier: Topic :: Security :: Cryptography
Requires-Python: >=3.6
